envtojson/__init__.py
envtojson/envtojson.py
envtojson-0.0.1.dist-info/DESCRIPTION.rst
envtojson-0.0.1.dist-info/METADATA
envtojson-0.0.1.dist-info/RECORD
envtojson-0.0.1.dist-info/WHEEL
envtojson-0.0.1.dist-info/entry_points.txt
envtojson-0.0.1.dist-info/metadata.json
envtojson-0.0.1.dist-info/top_level.txt
