Metadata-Version: 2.0
Name: envtojson
Version: 0.0.1
Summary: Write environment variables to a file in JSON format.
Home-page: https://github.com/techjacker/envtojson
Author: Andrew Griffiths
Author-email: mail@andrewgriffithsonline.com
License: MIT
Platform: UNKNOWN
Classifier: Development Status :: 5 - Production/Stable
Classifier: Natural Language :: English
Classifier: License :: OSI Approved :: MIT License
Classifier: Operating System :: OS Independent
Classifier: Programming Language :: Python
Classifier: Programming Language :: Python :: 3
Classifier: Programming Language :: Python :: 3.4
Classifier: Topic :: Text Processing :: Markup
